pyXor/__init__.py
PyXor-1.0.2.dist-info/LICENSE
PyXor-1.0.2.dist-info/METADATA
PyXor-1.0.2.dist-info/WHEEL
PyXor-1.0.2.dist-info/top_level.txt
PyXor-1.0.2.dist-info/RECORD
