Metadata-Version: 2.1
Name: PyXor
Version: 1.0.2
Summary: A xor encryption module
Home-page: https://github.com/LeRatGondin/PyXor
Author: LeRatGondin
Author-email: leratgondin1@gmail.com
Project-URL: Bug Tracker, https://github.com/LeRatGondin/PyXor/issues
Classifier: Programming Language :: Python :: 3
Classifier: License :: OSI Approved :: MIT License
Classifier: Operating System :: OS Independent
Requires-Python: >=3.6
License-File: LICENSE
